{
  "credit": "Made with Blockbench",
  "parent": "builtin/entity",
  "texture_size": [
    64,
    64
  ],
  "gui_light": "front",
  "display": {
    "thirdperson_righthand": {
      "rotation": [
        45,
        -145,
        0
      ],
      "translation": [
        0,
        -4,
        -4
      ],
      "scale": [
        0.5,
        0.5,
        0.5
      ]
    },
    "thirdperson_lefthand": {
      "rotation": [
        45,
        -145,
        0
      ],
      "translation": [
        0,
        -4,
        -4
      ],
      "scale": [
        0.5,
        0.5,
        0.5
      ]
    },
    "firstperson_righthand": {
      "rotation": [
        10,
        -145,
        0
      ],
      "translation": [
        0,
        -6,
        -4
      ],
      "scale": [
        0.5,
        0.5,
        0.5
      ]
    },
    "firstperson_lefthand": {
      "rotation": [
        10,
        -145,
        0
      ],
      "translation": [
        0,
        -6,
        -4
      ],
      "scale": [
        0.5,
        0.5,
        0.5
      ]
    },
    "ground": {
      "rotation": [
        45,
        45,
        0
      ],
      "translation": [
        0.25,
        0.5,
        -8
      ],
      "scale": [
        0.5,
        0.5,
        0.5
      ]
    },
    "gui": {
      "rotation": [
        -45,
        25,
        45
      ],
      "translation": [
        7,
        -8.25,
        0
      ],
      "scale": [
        0.5,
        0.5,
        0.5
      ]
    },
    "head": {
      "rotation": [
        -45,
        180,
        0
      ],
      "translation": [
        0,
        -6.5,
        1.5
      ],
      "scale": [
        0.5,
        0.5,
        0.5
      ]
    },
    "fixed": {
      "rotation": [
        0,
        -90,
        0
      ],
      "translation": [
        0,
        -23.25,
        -2.75
      ]
    }
  }
}